netbox_sensors/__init__.py
netbox_sensors/admin.py
netbox_sensors/columns.py
netbox_sensors/constants.py
netbox_sensors/filters.py
netbox_sensors/forms.py
netbox_sensors/middleware.py
netbox_sensors/models.py
netbox_sensors/navigation.py
netbox_sensors/signals.py
netbox_sensors/tables.py
netbox_sensors/urls.py
netbox_sensors/version.py
netbox_sensors/views.py
netbox_sensors/api/__init__.py
netbox_sensors/api/serializers.py
netbox_sensors/api/urls.py
netbox_sensors/api/views.py
netbox_sensors/api/modules/__init__.py
netbox_sensors/api/modules/module.py
netbox_sensors/api/modules/utils.py
netbox_sensors/api/modules/tests/__init__.py
netbox_sensors/api/modules/tests/database_setup.py
netbox_sensors/api/modules/tests/test_module.py
netbox_sensors/api/modules/tests/test_utils.py
netbox_sensors/api/modules/types_modules/__init__.py
netbox_sensors/api/modules/types_modules/abc_type_modules.py
netbox_sensors/api/modules/types_modules/all_data.py
netbox_sensors/api/modules/types_modules/average_data.py
netbox_sensors/api/modules/types_modules/average_transducer_types.py
netbox_sensors/api/modules/types_modules/device_location.py
netbox_sensors/api/modules/types_modules/device_locations.py
netbox_sensors/api/modules/types_modules/device_status.py
netbox_sensors/api/modules/types_modules/diagnostic_alert.py
netbox_sensors/api/modules/types_modules/download_data.py
netbox_sensors/api/modules/types_modules/dynamic_kpis.py
netbox_sensors/api/modules/types_modules/generate_menus.py
netbox_sensors/api/modules/types_modules/last_measurements.py
netbox_sensors/api/modules/types_modules/polar_graphs.py
netbox_sensors/api/modules/types_modules/status_gauge.py
netbox_sensors/api/modules/types_modules/tests/__init__.py
netbox_sensors/api/modules/types_modules/tests/database_setup.py
netbox_sensors/api/modules/types_modules/tests/test_abc_types_modules.py
netbox_sensors/api/modules/types_modules/tests/test_average_transducer_types.py
netbox_sensors-0.0.1.dist-info/METADATA
netbox_sensors-0.0.1.dist-info/WHEEL
netbox_sensors-0.0.1.dist-info/top_level.txt
netbox_sensors-0.0.1.dist-info/RECORD
