Metadata-Version: 2.1
Name: netbox-sensors
Version: 0.0.1
Summary: NetBox plugin for Sensores.
Home-page: https://github.com/netbox-community/netbox-sensors
Author: Óscar Hurtado
Author-email: ohurtadp@sens.solutions
License: MIT
Keywords: netbox,netbox-plugin,plugin
Classifier: Development Status :: 2 - Pre-Alpha
Classifier: Intended Audience :: Developers
Classifier: Natural Language :: English
Classifier: Programming Language :: Python :: 3
Classifier: Programming Language :: Python :: 3.8
Classifier: Programming Language :: Python :: 3.9
Classifier: Programming Language :: Python :: 3.10
Requires-Python: >=3.8
Requires-Dist: maya (==0.6.1)
Requires-Dist: python-dotenv (==1.0.0)
Requires-Dist: pandas (==2.2.2)
Requires-Dist: influxdb-client (==1.37.0)
Requires-Dist: django-pandas (==0.6.7)
Requires-Dist: freezegun (==1.2.2)
Requires-Dist: pika (==1.3.2)
Requires-Dist: amqpstorm[management] (==2.10.6)
Requires-Dist: cachetools (==5.3.3)
